atgsm/__init__.py
atgsm/atgsm.py
atgsm-0.4.dist-info/METADATA
atgsm-0.4.dist-info/WHEEL
atgsm-0.4.dist-info/licenses/LICENSE
atgsm-0.4.dist-info/RECORD
