Metadata-Version: 2.1
Name: atgsm
Version: 0.4
Summary: Python lib for AT GSM commands
Project-URL: Homepage, https://github.com/H4ckd4ddy/atgsm
Project-URL: Bug Tracker, https://github.com/H4ckd4ddy/atgsm/issues
License-File: LICENSE
Classifier: License :: OSI Approved :: MIT License
Classifier: Programming Language :: Python :: 3
Requires-Python: >=3.7
Requires-Dist: pyserial>=3.5
Requires-Dist: smspdudecoder>=2.0.0
